Workbook

Sheet Data
A1: Rating | B1: Name | C1: Symbol | D1: Rating Agency Name | E1: Date | F1: Sector | G1: currentRatio | H1: quickRatio | I1: cashRatio | J1: daysOfSalesOutstanding | K1: netProfitMargin | L1: pretaxProfitMargin | M1: grossProfitMargin | N1: operatingProfitMargin | O1: returnOnAssets | P1: returnOnCapitalEmployed | Q1: returnOnEquity | R1: assetTurnover | S1: fixedAssetTurnover | T1: debtEquityRatio | U1: debtRatio | V1: effectiveTaxRate | W1: freeCashFlowOperatingCashFlowRatio | X1: freeCashFlowPerShare | Y1: cashPerShare | Z1: companyEquityMultiplier | AA1: ebitPerRevenue | AB1: enterpriseValueMultiple | AC1: operatingCashFlowPerShare | AD1: operatingCashFlowSalesRatio | AE1: payablesTurnover | AF1: Date Parsed | AG1: Year | AH1: Quarter | AI1: Rating Score | AJ1: Rating Category
A2: A | B2: Whirlpool Corporation | C2: WHR | D2: Egan-Jones Ratings Company | E2: 11/27/2015 | F2: Consumer Durables | G2: 0.9458936 | H2: 0.42639463 | I2: 0.099690083 | J2: 44.203245 | K2: 0.037480255 | L2: 0.049351395 | M2: 0.17663108 | N2: 0.061509741 | O2: 0.041188848 | P2: 0.091514291 | Q2: 0.16508539 | R2: 1.0989479 | S2: 5.5355061 | T2: 3.0080118 | U2: 0.75049974 | V2: 0.20271581 | W2: 0.43755102 | X2: 6.8106734 | Y2: 9.8094028 | Z2: 4.0080118 | AA2: 0.049351395 | AB2: 7.0570881 | AC2: 15.565438 | AD2: 0.058637691 | AE2: 3.9066546 | AF2: 42335 | AG2: =YEAR(AF2) -> 2015 | AH2: ="Q"&ROUNDUP(MONTH(AF2)/3,0) -> Q4 | AI2: =INDEX(RatingLookup!$B$2:$B$11,MATCH(A2,RatingLookup!$A$2:$A$11,0)) -> 8 | AJ2: =INDEX(RatingLookup!$C$2:$C$11,MATCH(A2,RatingLookup!$A$2:$A$11,0)) -> Investment Grade
A3: BBB | B3: Whirlpool Corporation | C3: WHR | D3: Egan-Jones Ratings Company | E3: 2/13/2014 | F3: Consumer Durables | G3: 1.033559 | H3: 0.49823374 | I3: 0.2031204 | J3: 38.991156 | K3: 0.044062017 | L3: 0.048857158 | M3: 0.17571528 | N3: 0.0665459 | O3: 0.053203809 | P3: 0.1048 | Q3: 0.16795288 | R3: 1.2074756 | S3: 6.1719829 | T3: 2.1567831 | U3: 0.68322182 | V3: 0.074154853 | W3: 0.54199683 | X3: 8.6254729 | Y3: 17.40227 | Z3: 3.1567831 | AA3: 0.048857158 | AB3: 6.4606182 | AC3: 15.91425 | AD3: 0.067238532 | AE3: 4.0028461 | AF3: 41683 | AG3: =YEAR(AF3) -> 2014 | AH3: ="Q"&ROUNDUP(MONTH(AF3)/3,0) -> Q1 | AI3: =INDEX(RatingLookup!$B$2:$B$11,MATCH(A3,RatingLookup!$A$2:$A$11,0)) -> 7 | AJ3: =INDEX(RatingLookup!$C$2:$C$11,MATCH(A3,RatingLookup!$A$2:$A$11,0)) -> Investment Grade
A4: BBB | B4: Whirlpool Corporation | C4: WHR | D4: Fitch Ratings | E4: 3/6/2015 | F4: Consumer Durables | G4: 0.96370344 | H4: 0.45150542 | I4: 0.12209925 | J4: 50.841385 | K4: 0.03270934 | L4: 0.044333736 | M4: 0.1708434 | N4: 0.059782609 | O4: 0.03249675 | P4: 0.075954824 | Q4: 0.13306039 | R4: 0.99350065 | S4: 4.9917106 | T4: 3.0945752 | U4: 0.75577442 | V4: 0.21452894 | W4: 0.51318458 | X4: 9.6934866 | Y4: 13.103448 | Z4: 4.0945752 | AA4: 0.044333736 | AB4: 10.49197 | AC4: 18.888889 | AD4: 0.074426329 | AE4: 3.4835095 | AF4: 42069 | AG4: =YEAR(AF4) -> 2015 | AH4: ="Q"&ROUNDUP(MONTH(AF4)/3,0) -> Q1 | AI4: =INDEX(RatingLookup!$B$2:$B$11,MATCH(A4,RatingLookup!$A$2:$A$11,0)) -> 7 | AJ4: =INDEX(RatingLookup!$C$2:$C$11,MATCH(A4,RatingLookup!$A$2:$A$11,0)) -> Investment Grade
A5: BBB | B5: Whirlpool Corporation | C5: WHR | D5: Fitch Ratings | E5: 6/15/2012 | F5: Consumer Durables | G5: 1.0198507 | H5: 0.51040178 | I5: 0.17611561 | J5: 41.161738 | K5: 0.020893603 | L5: -0.012857602 | M5: 0.1380585 | N5: 0.042430087 | O5: 0.025690007 | P5: -0.027014858 | Q5: 0.09327912 | R5: 1.2295633 | S5: 6.0174081 | T5: 2.6309495 | U5: 0.72458995 | V5: 1.8166667 | W5: -0.14716981 | X5: -1.015625 | Y5: 14.440104 | Z5: 3.6309495 | AA5: -0.012857602 | AB5: 4.0807407 | AC5: 6.9010417 | AD5: 0.028393871 | AE5: 4.5811503 | AF5: 41075 | AG5: =YEAR(AF5) -> 2012 | AH5: ="Q"&ROUNDUP(MONTH(AF5)/3,0) -> Q2 | AI5: =INDEX(RatingLookup!$B$2:$B$11,MATCH(A5,RatingLookup!$A$2:$A$11,0)) -> 7 | AJ5: =INDEX(RatingLookup!$C$2:$C$11,MATCH(A5,RatingLookup!$A$2:$A$11,0)) -> Investment Grade
A6: BBB | B6: Whirlpool Corporation | C6: WHR | D6: Standard & Poor's Ratings Services | E6: 10/24/2016 | F6: Consumer Durables | G6: 0.95784391 | H6: 0.495432 | I6: 0.14160793 | J6: 47.761126 | K6: 0.04286128 | L6: 0.053769669 | M6: 0.17771986 | N6: 0.065353799 | O6: 0.046363494 | P6: 0.096945436 | Q6: 0.18604651 | R6: 1.0817104 | S6: 5.4377953 | T6: 3.0127802 | U6: 0.75079622 | V6: 0.16696589 | W6: 0.45137157 | X6: 7.1353482 | Y6: 14.257556 | Z6: 4.0127802 | AA6: 0.053769669 | AB6: 8.2935047 | AC6: 15.808147 | AD6: 0.05806545 | AE6: 3.8577899 | AF6: 42667 | AG6: =YEAR(AF6) -> 2016 | AH6: ="Q"&ROUNDUP(MONTH(AF6)/3,0) -> Q4 | AI6: =INDEX(RatingLookup!$B$2:$B$11,MATCH(A6,RatingLookup!$A$2:$A$11,0)) -> 7 | AJ6: =INDEX(RatingLookup!$C$2:$C$11,MATCH(A6,RatingLookup!$A$2:$A$11,0)) -> Investment Grade
A7: AA | B7: Schlumberger N.V. | C7: SLB | D7: Egan-Jones Ratings Company | E7: 7/18/2014 | F7: Energy | G7: 1.7419582 | H7: 1.3171558 | I7: 0.22079571 | J7: 83.931968 | K7: 0.11193907 | L7: 0.15724578 | M7: 0.23017703 | N7: 0.15724578 | O7: 0.081280641 | P7: 0.14487559 | Q7: 0.14367239 | R7: 0.72611503 | S7: 3.155365 | T7: 0.76760898 | U7: 0.43426402 | V7: 0.25238906 | W7: 0.64484145 | X7: 5.5745174 | Y7: 5.792278 | Z7: 1.767609 | AA7: 0.15724578 | AB7: 9.833295 | AC7: 8.6447876 | AD7: 0.23044463 | AE7: 4.0447761 | AF7: 41838 | AG7: =YEAR(AF7) -> 2014 | AH7: ="Q"&ROUNDUP(MONTH(AF7)/3,0) -> Q3 | AI7: =INDEX(RatingLookup!$B$2:$B$11,MATCH(A7,RatingLookup!$A$2:$A$11,0)) -> 9 | AJ7: =INDEX(RatingLookup!$C$2:$C$11,MATCH(A7,RatingLookup!$A$2:$A$11,0)) -> Investment Grade
A8: AA | B8: Schlumberger N.V. | C8: SLB | D8: Egan-Jones Ratings Company | E8: 5/13/2014 | F8: Energy | G8: 1.9390018 | H8: 1.4689094 | I8: 0.2567098 | J8: 92.705452 | K8: 0.14872089 | L8: 0.15117307 | M8: 0.2194804 | N8: 0.14872089 | O8: 0.10032787 | P8: 0.12772749 | Q8: 0.17056424 | R8: 0.67460507 | S8: 2.9985427 | T8: 0.70006841 | U8: 0.41178838 | V8: 0.27005699 | W8: 0.59715979 | X8: 4.4179894 | Y8: 6.3265306 | Z8: 1.7000684 | AA8: 0.15117307 | AB8: 12.140376 | AC8: 7.3983371 | AD8: 0.21623293 | AE8: 3.9980763 | AF8: 41772 | AG8: =YEAR(AF8) -> 2014 | AH8: ="Q"&ROUNDUP(MONTH(AF8)/3,0) -> Q2 | AI8: =INDEX(RatingLookup!$B$2:$B$11,MATCH(A8,RatingLookup!$A$2:$A$11,0)) -> 9 | AJ8: =INDEX(RatingLookup!$C$2:$C$11,MATCH(A8,RatingLookup!$A$2:$A$11,0)) -> Investment Grade
A9: A | B9: Schlumberger N.V. | C9: SLB | D9: Egan-Jones Ratings Company | E9: 7/23/2015 | F9: Energy | G9: 1.905814 | H9: 1.5447914 | I9: 0.19779052 | J9: 90.336857 | K9: 0.058407329 | L9: 0.081212121 | M9: 0.20166314 | N9: 0.081212121 | O9: 0.030468348 | P9: 0.053466706 | Q9: 0.058148346 | R9: 0.52165282 | S9: 2.6444279 | T9: 0.90848371 | U9: 0.47602382 | V9: 0.25893787 | W9: 0.72629188 | X9: 5.047356 | Y9: 10.287293 | Z9: 1.9084837 | AA9: 0.081212121 | AB9: 15.264562 | AC9: 6.949487 | AD9: 0.24820296 | AE9: 3.6651999 | AF9: 42208 | AG9: =YEAR(AF9) -> 2015 | AH9: ="Q"&ROUNDUP(MONTH(AF9)/3,0) -> Q3 | AI9: =INDEX(RatingLookup!$B$2:$B$11,MATCH(A9,RatingLookup!$A$2:$A$11,0)) -> 8 | AJ9: =INDEX(RatingLookup!$C$2:$C$11,MATCH(A9,RatingLookup!$A$2:$A$11,0)) -> Investment Grade
A10: AA | B10: Honeywell International Inc. | C10: HON | D10: Egan-Jones Ratings Company | E10: 4/29/2014 | F10: Capital Goods | G10: 1.4924194 | H10: 1.1298216 | I10: 0.45285946 | J10: 74.102804 | K10: 0.10047369 | L10: 0.13857381 | M10: 0.27374216 | N10: 0.13857381 | O10: 0.086365137 | P10: 0.17316183 | Q10: 0.2246522 | R10: 0.85957962 | S10: 7.3995832 | T10: 1.6011908 | U10: 0.61556069 | V10: 0.26792313 | W10: 0.78154556 | X10: 4.3082401 | Y10: 10.2912 | Z10: 2.6011908 | AA10: 0.13857381 | AB10: 10.897998 | AC10: 5.5124619 | AD10: 0.11099731 | AE10: 5.4820255 | AF10: 41758 | AG10: =YEAR(AF10) -> 2014 | AH10: ="Q"&ROUNDUP(MONTH(AF10)/3,0) -> Q2 | AI10: =INDEX(RatingLookup!$B$2:$B$11,MATCH(A10,RatingLookup!$A$2:$A$11,0)) -> 9 | AJ10: =INDEX(RatingLookup!$C$2:$C$11,MATCH(A10,RatingLookup!$A$2:$A$11,0)) -> Investment Grade
A11: A | B11: Honeywell International Inc. | C11: HON | D11: Moody's Investors Service | E11: 2/16/2016 | F11: Capital Goods | G11: 1.0915573 | H11: 0.85096075 | I11: 0.29693539 | J11: 76.394469 | K11: 0.12358415 | L11: 0.17070579 | M11: 0.30673129 | N11: 0.17070579 | O11: 0.096682618 | P11: 0.21282921 | Q11: 0.26078871 | R11: 0.78232217 | S11: 6.6645362 | T11: 1.6973691 | U11: 0.62926839 | V11: 0.26404494 | W11: 0.80326366 | X11: 5.6181072 | Y11: 9.6922288 | Z11: 2.6973691 | AA11: 0.17070579 | AB11: 10.362903 | AC11: 6.9941011 | AD11: 0.14136492 | AE11: 4.7933692 | AF11: 42416 | AG11: =YEAR(AF11) -> 2016 | AH11: ="Q"&ROUNDUP(MONTH(AF11)/3,0) -> Q1 | AI11: =INDEX(RatingLookup!$B$2:$B$11,MATCH(A11,RatingLookup!$A$2:$A$11,0)) -> 8 | AJ11: =INDEX(RatingLookup!$C$2:$C$11,MATCH(A11,RatingLookup!$A$2:$A$11,0)) -> Investment Grade
A12: AA | B12: Honeywell International Inc. | C12: HON | D12: Egan-Jones Ratings Company | E12: 4/21/2015 | F12: Capital Goods | G12: 1.5021323 | H12: 1.1550802 | I12: 0.47106207 | J12: 72.083561 | K12: 0.10517045 | L12: 0.14434575 | M12: 0.28157098 | N12: 0.14434575 | O12: 0.093265275 | P12: 0.1896473 | Q12: 0.24007476 | R12: 0.88680117 | S12: 7.4876463 | T12: 1.5741066 | U12: 0.6115157 | V12: 0.25592987 | W12: 0.78224522 | X12: 5.0101989 | Y12: 11.606323 | Z12: 2.5741066 | AA12: 0.14434575 | AB12: 10.847238 | AC12: 6.4048955 | AD12: 0.12464646 | AE12: 5.3973905 | AF12: 42115 | AG12: =YEAR(AF12) -> 2015 | AH12: ="Q"&ROUNDUP(MONTH(AF12)/3,0) -> Q2 | AI12: =INDEX(RatingLookup!$B$2:$B$11,MATCH(A12,RatingLookup!$A$2:$A$11,0)) -> 9 | AJ12: =INDEX(RatingLookup!$C$2:$C$11,MATCH(A12,RatingLookup!$A$2:$A$11,0)) -> Investment Grade
A13: A | B13: Sysco Corporation | C13: SYY | D13: Egan-Jones Ratings Company | E13: 6/1/2015 | F13: Consumer Non-Durables | G13: 1.5298851 | H13: 0.87272938 | I13: 0.094569824 | J13: 26.668485 | K13: 0.020025771 | L13: 0.031722448 | M13: 0.17587303 | N13: 0.034119393 | O13: 0.070742447 | P13: 0.16767845 | Q13: 0.1768724 | R13: 3.5325705 | S13: 11.671142 | T13: 1.5002302 | U13: 0.60003683 | V13: 0.36871927 | W13: 0.64951719 | X13: 1.6546565 | Y13: 0.70487099 | Z13: 2.5002302 | AA13: 0.031722448 | AB13: 11.074542 | AC13: 2.5475177 | AD13: 0.032092015 | AE13: 13.541257 | AF13: 42156 | AG13: =YEAR(AF13) -> 2015 | AH13: ="Q"&ROUNDUP(MONTH(AF13)/3,0) -> Q2 | AI13: =INDEX(RatingLookup!$B$2:$B$11,MATCH(A13,RatingLookup!$A$2:$A$11,0)) -> 8 | AJ13: =INDEX(RatingLookup!$C$2:$C$11,MATCH(A13,RatingLookup!$A$2:$A$11,0)) -> Investment Grade
... A2030: CCC | B2030: Cresud S.A.C.I.F. y A. | C2030: CRESY | D2030: Fitch Ratings | E2030: 8/1/2014 | F2030: Finance | G2030: 1.0850071 | H2030: 1.0263745 | I2030: 0.20348955 | J2030: 151.66051 | K2030: -0.2319722 | L2030: -0.31646394 | M2030: 0.39661164 | N2030: 0.20742832 | O2030: -0.03715041 | P2030: 0.05856669 | Q2030: -0.14634146 | R2030: 0.16015027 | S2030: 0.24764671 | T2030: 2.1541518 | U2030: 0.54685543 | V2030: 0.26698696 | W2030: 1.1014617 | X2030: 2.4878167 | Y2030: 6.1098137 | Z2030: 3.9391614 | AA2030: 0.30299739 | AB2030: 9.6040607 | AC2030: 2.2586502 | AD2030: 0.25260643 | AE2030: 1.8656817 | AF2030: 41852 | AG2030: =YEAR(AF2030) -> 2014 | AH2030: ="Q"&ROUNDUP(MONTH(AF2030)/3,0) -> Q3 | AI2030: =INDEX(RatingLookup!$B$2:$B$11,MATCH(A2030,RatingLookup!$A$2:$A$11,0)) -> 4 | AJ2030: =INDEX(RatingLookup!$C$2:$C$11,MATCH(A2030,RatingLookup!$A$2:$A$11,0)) -> Speculative Grade

Sheet RatingLookup
A1: Rating | B1: Rating Score | C1: Rating Category
A2: AAA | B2: 10 | C2: Investment Grade
A3: AA | B3: 9 | C3: Investment Grade
A4: A | B4: 8 | C4: Investment Grade
A5: BBB | B5: 7 | C5: Investment Grade
A6: BB | B6: 6 | C6: Speculative Grade
A7: B | B7: 5 | C7: Speculative Grade
A8: CCC | B8: 4 | C8: Speculative Grade
A9: CC | B9: 3 | C9: Speculative Grade
A10: C | B10: 2 | C10: Speculative Grade
A11: D | B11: 1 | C11: Default

Sheet DAX Measures (Reference)
A1: Measure Name | B1: DAX Formula (paste into Power BI > New Measure)
A2: Total Companies | B2: Total Companies = DISTINCTCOUNT(Data[Name])
A3: Total Ratings | B3: Total Ratings = COUNTROWS(Data)
A4: Avg Rating Score | B4: Avg Rating Score = AVERAGE(Data[Rating Score])
A5: % Investment Grade | B5: % Investment Grade = DIVIDE(CALCULATE(COUNTROWS(Data), Data[Rating Category]="Investment Grade"), COUNTROWS(Data))
A6: % Speculative Grade | B6: % Speculative Grade = DIVIDE(CALCULATE(COUNTROWS(Data), Data[Rating Category]="Speculative Grade"), COUNTROWS(Data))
A7: % Default | B7: % Default = DIVIDE(CALCULATE(COUNTROWS(Data), Data[Rating Category]="Default"), COUNTROWS(Data))
A8: Avg ROE | B8: Avg ROE = AVERAGE(Data[returnOnEquity])
A9: Avg ROA | B9: Avg ROA = AVERAGE(Data[returnOnAssets])
A10: Avg Debt to Equity | B10: Avg Debt to Equity = AVERAGE(Data[debtEquityRatio])
A11: Avg Net Profit Margin | B11: Avg Net Profit Margin = AVERAGE(Data[netProfitMargin])
A12: YoY Avg Rating Score | B12: YoY Avg Rating Score = VAR CurYear = [Avg Rating Score] VAR PrevYear = CALCULATE([Avg Rating Score], SAMEPERIODLASTYEAR(Data[Date Parsed])) RETURN CurYear - PrevYear
A13: Companies per Agency | B13: Companies per Agency = DISTINCTCOUNT(Data[Name])
A16: Notes:
A17: 1. Import the "Data" sheet into Power BI. Set "Date Parsed" column type to Date.
A18: 2. Do NOT import "RatingLookup" as a separate model table -- it was only used to build Rating Score/Category via Excel formulas. You may optionally load it and relate for a proper star schema.
A19: 3. Rating Score: AAA=10 (best) down to D=1 (default) -- use for trend lines, avg score by sector/agency.
A20: 4. Rating Category groups ratings into Investment Grade / Speculative Grade / Default -- use for high-level KPI cards.
